Workbook

Sheet Incident_Data
A1: Incident_ID | B1: Date_Reported | C1: Description | D1: Category | E1: Severity | F1: Department | G1: Financial_Impact_GBP | H1: Detection_Method | I1: Status
A2: OPR-0001 | B2: 45301 | C2: Fire suppression system triggered at Corporate Banking branch causing equipment damage. | D2: Damage to Physical Assets | E2: High | F2: Retail Banking | G2: 414693 | H2: Site Inspection | I2: Closed
A3: OPR-0002 | B3: 45322 | C3: Phishing attack resulted in unauthorised access to 282 customer accounts. | D3: External Fraud | E3: Medium | F3: Corporate Banking | G3: 19328 | H3: Customer Complaint | I3: Resolved
A4: OPR-0003 | B4: 45324 | C4: Flooding at IT Operations data centre caused disruption to on-site server infrastructure. | D4: Damage to Physical Assets | E4: Low | F4: Compliance | G4: 3286 | H4: Site Inspection | I4: Open
A5: OPR-0004 | B5: 45332 | C5: Customer data used for marketing without valid consent under GDPR for 368 clients. | D5: Clients, Products & Business Practices | E5: High | F5: Treasury | G5: 420997 | H5: Internal Audit | I5: Escalated
A6: OPR-0005 | B6: 45344 | C6: Data breach exposed personal information of 190 customers via online banking portal vulnerability. | D6: Cybersecurity Incident | E6: Low | F6: Risk Management | G6: 4602 | H6: Penetration Test | I6: Resolved
A7: OPR-0006 | B7: 45354 | C7: Employee falsified expense claims totalling £4000 over a three-month period. | D7: Internal Fraud | E7: High | F7: Compliance | G7: 79971 | H7: Internal Audit | I7: Resolved
A8: OPR-0007 | B8: 45361 | C8: Regulatory review identified inadequate suitability assessment for credit cards sales. | D8: Clients, Products & Business Practices | E8: Critical | F8: Human Resources | G8: 4755773 | H8: Compliance Monitoring | I8: Resolved
A9: OPR-0008 | B9: 45364 | C9: Third-party cloud provider outage disrupted access to online banking portal platform. | D9: Business Disruption & System Failures | E9: Medium | F9: Retail Banking | G9: 20003 | H9: System Monitoring Alert | I9: Closed
A10: OPR-0009 | B10: 45365 | C10: Vandalism reported at ATM located at Treasury branch, machine offline for repair. | D10: Damage to Physical Assets | E10: High | F10: Retail Banking | G10: 136991 | H10: Site Inspection | I10: Resolved
A11: OPR-0010 | B11: 45369 | C11: Health and safety inspection identified non-compliance in IT Operations office premises. | D11: Employment Practices & Workplace Safety | E11: Medium | F11: Corporate Banking | G11: 31401 | H11: Health & Safety Audit | I11: Resolved
A12: OPR-0011 | B12: 45373 | C12: Third party used stolen identity documents to open 391 fraudulent accounts. | D12: External Fraud | E12: High | F12: Retail Banking | G12: 184177 | H12: Customer Complaint | I12: Closed
A13: OPR-0012 | B13: 45375 | C13: Staff member sustained injury during Treasury office relocation activities. | D13: Employment Practices & Workplace Safety | E13: Medium | F13: Compliance | G13: 19715 | H13: HR Report | I13: Under Investigation
... A201: OPR-0200 | B201: 46200 | C201: Mis-selling complaint upheld regarding personal loans sold to retail customers. | D201: Clients, Products & Business Practices | E201: Low | F201: Human Resources | G201: 1111 | H201: Internal Audit | I201: Resolved

Sheet Data_Dictionary
A1: Data Dictionary – Synthetic Operational Risk Incident Dataset
A3: Field | B3: Type | C3: Description | D3: Example
A4: Incident_ID | B4: Text | C4: Unique identifier for each incident record | D4: OPR-0001
A5: Date_Reported | B5: Date | C5: Date the incident was reported/logged | D5: 14/03/2025
A6: Description | B6: Text (free text) | C6: Narrative description used as input for NLP classification | D6: "Phishing attack resulted in unauthorised access to 42 customer accounts."
A7: Category | B7: Categorical | C7: Basel II operational risk event type (target label) | D7: External Fraud
A8: Severity | B8: Categorical (ordinal) | C8: Impact severity: Low / Medium / High / Critical | D8: High
A9: Department | B9: Categorical | C9: Business unit where incident originated | D9: Payments
A10: Financial_Impact_GBP | B10: Numeric | C10: Estimated financial impact in GBP | D10: 125000
A11: Detection_Method | B11: Categorical | C11: How the incident was identified | D11: SOC Monitoring
A12: Status | B12: Categorical | C12: Current lifecycle status of the incident | D12: Under Investigation
A15: Notes on data generation methodology:
A16: 1. Categories follow the Basel II operational risk event-type taxonomy, extended with a Cybersecurity Incident category to reflect current literature gaps.
A17: 2. Descriptions are generated from templated sentence structures with randomised entities (department, system, amount, etc.) to provide realistic linguistic variety for NLP model training.
A18: 3. Severity distributions per category are weighted to loosely reflect real-world skew reported in public risk literature (e.g. process/execution errors are frequent but lower severity; cyber incidents are less frequent but higher severity).
A19: 4. Financial impact is generated from severity-linked ranges, not derived from real institutional data.
A20: 5. This dataset is entirely synthetic and contains no real institution, customer, or employee data. It is intended for prototype development and model testing only, in line with confidentiality and ethical constraints discussed with the supervisor.

Sheet Category_Summary
A1: Summary Statistics by Risk Category
A3: Category | B3: Incident_Count | C3: Avg_Financial_Impact_GBP | D3: High_or_Critical_Count | E3: % of Total Incidents
A4: Internal Fraud | B4: =COUNTIF(Incident_Data!$D$2:$D$201,A4) -> 14 | C4: =ROUND(AVERAGEIF(Incident_Data!$D$2:$D$201,A4,Incident_Data!$G$2:$G$201),0) -> 651382 | D4: =COUNTIFS(Incident_Data!$D$2:$D$201,A4,Incident_Data!$E$2:$E$201,"High")+COUNTIFS(Incident_Data!$D$2:$D$201,A4,Incident_Data!$E$2:$E$201,"Critical") -> 9 | E4: =B4/200 -> 0.07
A5: External Fraud | B5: =COUNTIF(Incident_Data!$D$2:$D$201,A5) -> 20 | C5: =ROUND(AVERAGEIF(Incident_Data!$D$2:$D$201,A5,Incident_Data!$G$2:$G$201),0) -> 255383 | D5: =COUNTIFS(Incident_Data!$D$2:$D$201,A5,Incident_Data!$E$2:$E$201,"High")+COUNTIFS(Incident_Data!$D$2:$D$201,A5,Incident_Data!$E$2:$E$201,"Critical") -> 10 | E5: =B5/200 -> 0.1
A6: Employment Practices & Workplace Safety | B6: =COUNTIF(Incident_Data!$D$2:$D$201,A6) -> 28 | C6: =ROUND(AVERAGEIF(Incident_Data!$D$2:$D$201,A6,Incident_Data!$G$2:$G$201),0) -> 389128 | D6: =COUNTIFS(Incident_Data!$D$2:$D$201,A6,Incident_Data!$E$2:$E$201,"High")+COUNTIFS(Incident_Data!$D$2:$D$201,A6,Incident_Data!$E$2:$E$201,"Critical") -> 7 | E6: =B6/200 -> 0.14
A7: Clients, Products & Business Practices | B7: =COUNTIF(Incident_Data!$D$2:$D$201,A7) -> 35 | C7: =ROUND(AVERAGEIF(Incident_Data!$D$2:$D$201,A7,Incident_Data!$G$2:$G$201),0) -> 562417 | D7: =COUNTIFS(Incident_Data!$D$2:$D$201,A7,Incident_Data!$E$2:$E$201,"High")+COUNTIFS(Incident_Data!$D$2:$D$201,A7,Incident_Data!$E$2:$E$201,"Critical") -> 19 | E7: =B7/200 -> 0.175
A8: Damage to Physical Assets | B8: =COUNTIF(Incident_Data!$D$2:$D$201,A8) -> 26 | C8: =ROUND(AVERAGEIF(Incident_Data!$D$2:$D$201,A8,Incident_Data!$G$2:$G$201),0) -> 664134 | D8: =COUNTIFS(Incident_Data!$D$2:$D$201,A8,Incident_Data!$E$2:$E$201,"High")+COUNTIFS(Incident_Data!$D$2:$D$201,A8,Incident_Data!$E$2:$E$201,"Critical") -> 14 | E8: =B8/200 -> 0.13
A9: Business Disruption & System Failures | B9: =COUNTIF(Incident_Data!$D$2:$D$201,A9) -> 30 | C9: =ROUND(AVERAGEIF(Incident_Data!$D$2:$D$201,A9,Incident_Data!$G$2:$G$201),0) -> 338299 | D9: =COUNTIFS(Incident_Data!$D$2:$D$201,A9,Incident_Data!$E$2:$E$201,"High")+COUNTIFS(Incident_Data!$D$2:$D$201,A9,Incident_Data!$E$2:$E$201,"Critical") -> 10 | E9: =B9/200 -> 0.15
A10: Execution, Delivery & Process Management | B10: =COUNTIF(Incident_Data!$D$2:$D$201,A10) -> 28 | C10: =ROUND(AVERAGEIF(Incident_Data!$D$2:$D$201,A10,Incident_Data!$G$2:$G$201),0) -> 455738 | D10: =COUNTIFS(Incident_Data!$D$2:$D$201,A10,Incident_Data!$E$2:$E$201,"High")+COUNTIFS(Incident_Data!$D$2:$D$201,A10,Incident_Data!$E$2:$E$201,"Critical") -> 13 | E10: =B10/200 -> 0.14
A11: Cybersecurity Incident | B11: =COUNTIF(Incident_Data!$D$2:$D$201,A11) -> 19 | C11: =ROUND(AVERAGEIF(Incident_Data!$D$2:$D$201,A11,Incident_Data!$G$2:$G$201),0) -> 1109866 | D11: =COUNTIFS(Incident_Data!$D$2:$D$201,A11,Incident_Data!$E$2:$E$201,"High")+COUNTIFS(Incident_Data!$D$2:$D$201,A11,Incident_Data!$E$2:$E$201,"Critical") -> 10 | E11: =B11/200 -> 0.095
A12: TOTAL | B12: =SUM(B4:B11) -> 200 | E12: =SUM(E4:E11) -> 1
